origami/blast.py
origami/circos_tools.py
origami/circularize.py
origami/cli.py
origami/config.py
origami/dot.py
origami/genome_stat.py
origami/hits.py
origami/io.py
origami/linear.py
origami/logging_setup.py
origami/main.py
origami/models.py
origami/pairing.py
origami/paths.py
origami/report.py
origami/rotate.py
origami/setup.py
origami/trim.py
origami/utils.py
origami/workflows.py
origami/data/__init__.py
origami/data/clustered_DB/OriC_clustered100_DB.nhr
origami/data/clustered_DB/OriC_clustered100_DB.nin
origami/data/clustered_DB/OriC_clustered100_DB.nsq
origami/data/clustered_DB/OriC_clustered_100.fasta
origami/data/clustered_DB/__init__.py
origami/data/clustered_DB/dnaA_clustered100_DB.nhr
origami/data/clustered_DB/dnaA_clustered100_DB.nin
origami/data/clustered_DB/dnaA_clustered100_DB.nsq
origami/data/clustered_DB/dnaA_clustered_100_modified_headers.fasta
origenomi-0.1.3.dist-info/METADATA
origenomi-0.1.3.dist-info/WHEEL
origenomi-0.1.3.dist-info/entry_points.txt
origenomi-0.1.3.dist-info/top_level.txt
origenomi-0.1.3.dist-info/RECORD
