Metadata-Version: 2.4
Name: origenomi
Version: 0.1.3
Summary: Trim circular overlaps, find dnaA/oriC, rotate sequences, and report.
Author: You
Requires-Python: >=3.9
Requires-Dist: biopython>=1.83
Requires-Dist: numpy>=1.26
Requires-Dist: matplotlib>=3.7
